package/__init__.py
package/fetch_data.py
AgriTech-0.1.dist-info/LICENCE
AgriTech-0.1.dist-info/METADATA
AgriTech-0.1.dist-info/WHEEL
AgriTech-0.1.dist-info/entry_points.txt
AgriTech-0.1.dist-info/top_level.txt
AgriTech-0.1.dist-info/RECORD
