Metadata-Version: 2.1
Name: AgriTech
Version: 0.1
Summary: Python package for getting data from Aws dataset
Home-page: https://github.com/nebasam/AgriTech---USGS-LIDAR-package
Author: Nebiyu Samuel
Author-email: neba.samuel17@gmail.com
License: MIT
Platform: UNKNOWN
Classifier: License :: OSI Approved :: MIT License
Classifier: Programming Language :: Python :: 3.6
Classifier: Programming Language :: Python :: 3.7
Classifier: Programming Language :: Python :: 3.8
License-File: LICENCE
